dhcpy/ClientClass.py
dhcpy/Logger.py
dhcpy/__init__.py
dhcpy/allocator.py
dhcpy/allocatorType.py
dhcpy/dhcpOption.py
dhcpy/dhcpQueueControl.py
dhcpy/dhcp_service.py
dhcpy/expiredLeaseProcessing.py
dhcpy/hookLibrary.py
dhcpy/interfacesConfig.py
dhcpy/leaseDatabase.py
dhcpy/multiThreading.py
dhcpy/pool.py
dhcpy/sanityChecks.py
dhcpy/sendToServer.py
dhcpy/server.py
dhcpy/serverID.py
dhcpy/subnet.py
dhcpy/subnetType.py
dhcpy-0.0.7.dist-info/METADATA
dhcpy-0.0.7.dist-info/WHEEL
dhcpy-0.0.7.dist-info/licenses/LICENSE
dhcpy-0.0.7.dist-info/RECORD
