Metadata-Version: 2.3
Name: dhcpy
Version: 0.0.7
Summary: A library for working with Kea using requests and json
Project-URL: Homepage, https://github.com/botheredtodd/dhcpy.git
Project-URL: Documentation, https://botheredtodd.github.io/dhcpy/
Project-URL: Repository, https://github.com/botheredtodd/dhcpy.git
Project-URL: Bug Tracker, https://github.com/botheredtodd/dhcpy/issues
Author-email: Todd Balsley <todd.balsley@cox.com>
Maintainer-email: Todd Balsley <todd.balsley@cox.com>
License: MIT License
License-File: LICENSE
Keywords: KEA,dhcp
Classifier: Development Status :: 3 - Alpha
Classifier: Programming Language :: Python
Requires-Dist: requests
